untie/TIE_classes.py
untie/TIE_core.py
untie/TIE_general.py
untie/TIE_load.py
untie/TIE_visual.py
untie/__init__.py
untie/data/BedrockColors/Bellelay.txt
untie/data/BedrockColors/Biaufond.txt
untie/data/BedrockColors/Boltigen.txt
untie/data/BedrockColors/Chasseral.txt
untie/data/BedrockColors/Mendrisio.txt
untie/data/BedrockColors/Muotatal.txt
untie/data/BedrockColors/Saignelegier.txt
untie/data/BedrockColors/Samnaun.txt
untie/data/BedrockColors/StUrsanne.txt
untie/data/geocover/GC-V-V2-143/Data/SHP/de/Bedrock_PLG.cpg
untie/data/geocover/GC-V-V2-143/Data/SHP/de/Bedrock_PLG.dbf
untie/data/geocover/GC-V-V2-143/Data/SHP/de/Bedrock_PLG.prj
untie/data/geocover/GC-V-V2-143/Data/SHP/de/Bedrock_PLG.qpj
untie/data/geocover/GC-V-V2-143/Data/SHP/de/Bedrock_PLG.shp
untie/data/geocover/GC-V-V2-143/Data/SHP/de/Bedrock_PLG.shx
untie/data/geocover/GC-V-V2-143/Data/SHP/de/Planar_Structures_PT.cpg
untie/data/geocover/GC-V-V2-143/Data/SHP/de/Planar_Structures_PT.dbf
untie/data/geocover/GC-V-V2-143/Data/SHP/de/Planar_Structures_PT.prj
untie/data/geocover/GC-V-V2-143/Data/SHP/de/Planar_Structures_PT.shp
untie/data/geocover/GC-V-V2-143/Data/SHP/de/Planar_Structures_PT.shx
untie/data/geocover/GC-V-V2-143/Data/SHP/de/Planar_Structures_PT.shz
untie/data/geocover/GC-V-V2-143/Data/SHP/de/Tectonic_Boundaries_L.cpg
untie/data/geocover/GC-V-V2-143/Data/SHP/de/Tectonic_Boundaries_L.dbf
untie/data/geocover/GC-V-V2-143/Data/SHP/de/Tectonic_Boundaries_L.prj
untie/data/geocover/GC-V-V2-143/Data/SHP/de/Tectonic_Boundaries_L.shp
untie/data/geocover/GC-V-V2-143/Data/SHP/de/Tectonic_Boundaries_L.shx
untie/data/geocover/GC-V-V2-143/Data/SHP/de/Tectonic_Boundaries_L.shz
untie/data/geocover/GC-V-V2-143/Metadata/143_Boltigen.cpg
untie/data/geocover/GC-V-V2-143/Metadata/143_Boltigen.dbf
untie/data/geocover/GC-V-V2-143/Metadata/143_Boltigen.prj
untie/data/geocover/GC-V-V2-143/Metadata/143_Boltigen.shp
untie/data/geocover/GC-V-V2-143/Metadata/143_Boltigen.shx
untie/data/swissALTI3d/swiss_1226_1_a.tif
untie-0.0.9.dist-info/LICENSE.md
untie-0.0.9.dist-info/METADATA
untie-0.0.9.dist-info/WHEEL
untie-0.0.9.dist-info/entry_points.txt
untie-0.0.9.dist-info/top_level.txt
untie-0.0.9.dist-info/RECORD
